open_assistants/__init__.py
open_assistants/example.py
open_assistants-0.0.1.dist-info/LICENSE
open_assistants-0.0.1.dist-info/METADATA
open_assistants-0.0.1.dist-info/WHEEL
open_assistants-0.0.1.dist-info/top_level.txt
open_assistants-0.0.1.dist-info/RECORD
