Metadata-Version: 2.1
Name: open-assistants
Version: 0.0.1
Summary: An Open-Source Edition of the Assistants API
Author-email: Qiang Li <qiangli@microsoft.com>
Classifier: Programming Language :: Python :: 3
Classifier: License :: OSI Approved :: MIT License
Classifier: Operating System :: OS Independent
Requires-Python: >=3.7
License-File: LICENSE
